ordinal/__init__.py
ordinal-1.0.3.dist-info/LICENSE
ordinal-1.0.3.dist-info/METADATA
ordinal-1.0.3.dist-info/WHEEL
ordinal-1.0.3.dist-info/top_level.txt
ordinal-1.0.3.dist-info/RECORD
